gefpy/__init__.py
gefpy/bgef_creater_cy.cpython-39-x86_64-linux-gnu.so
gefpy/bgef_reader_cy.cpython-39-x86_64-linux-gnu.so
gefpy/bgef_reader_helper.py
gefpy/bgef_writer_cy.cpython-39-x86_64-linux-gnu.so
gefpy/cell_exp_reader.py
gefpy/cell_mask_annotation.py
gefpy/cgef_adjust_cy.cpython-39-x86_64-linux-gnu.so
gefpy/cgef_adjust_helper.py
gefpy/cgef_reader_cy.cpython-39-x86_64-linux-gnu.so
gefpy/cgef_writer_cy.cpython-39-x86_64-linux-gnu.so
gefpy/fish.py
gefpy/gef_to_gem_cy.cpython-39-x86_64-linux-gnu.so
gefpy/gene_exp_cy.cpython-39-x86_64-linux-gnu.so
gefpy/lasso_generate_script.py
gefpy/lasso_utils.py
gefpy/plot.py
gefpy/stereo_map_extension_cy.cpython-39-x86_64-linux-gnu.so
gefpy/stereo_map_extension_cy.pyi
gefpy/utils.py
gefpy-1.2.6.dist-info/METADATA
gefpy-1.2.6.dist-info/WHEEL
gefpy-1.2.6.dist-info/top_level.txt
gefpy-1.2.6.dist-info/RECORD
gefpy.libs/libtiff-07e925da.so.6.0.2
gefpy.libs/libjpeg-43436dd5.so.62.1.0
gefpy.libs/libtiff-b6eb22fb.so.5.2.0
gefpy.libs/libpng15-ce838cd1.so.15.13.0
gefpy.libs/libzstd-8d126cbb.so.1.5.5
gefpy.libs/libgef-130d75c8.so
gefpy.libs/libjbig-78348776.so.2.0
gefpy.libs/liblzma-004595ca.so.5.2.2
